MANIFEST.in
README.md
pyproject.toml
setup.cfg
setup.py
locscale/__init__.py
locscale/__version__.py
locscale/disclaimer.txt
locscale/main.py
locscale.egg-info/PKG-INFO
locscale.egg-info/SOURCES.txt
locscale.egg-info/dependency_links.txt
locscale.egg-info/entry_points.txt
locscale.egg-info/not-zip-safe
locscale.egg-info/requires.txt
locscale.egg-info/top_level.txt
locscale/automate/__init__.py
locscale/automate/tools.py
locscale/emmernet/__init__.py
locscale/emmernet/emmernet_functions.py
locscale/emmernet/prepare_inputs.py
locscale/emmernet/run_emmernet.py
locscale/emmernet/utils.py
locscale/include/__init__.py
locscale/include/confidenceMapUtil/FDRutil.py
locscale/include/confidenceMapUtil/__init__.py
locscale/include/confidenceMapUtil/confidenceMapMain.py
locscale/include/confidenceMapUtil/locscaleUtil.py
locscale/include/confidenceMapUtil/mapUtil.py
locscale/include/emmer/__init__.py
locscale/include/emmer/headers.py
locscale/include/emmer/ndimage/__init__.py
locscale/include/emmer/ndimage/common_map_headers.py
locscale/include/emmer/ndimage/emdb_class.py
locscale/include/emmer/ndimage/fft_util.py
locscale/include/emmer/ndimage/filter.py
locscale/include/emmer/ndimage/fsc_util.py
locscale/include/emmer/ndimage/map_quality_tools.py
locscale/include/emmer/ndimage/map_tools.py
locscale/include/emmer/ndimage/map_utils.py
locscale/include/emmer/ndimage/plotContourMap.py
locscale/include/emmer/ndimage/plots.py
locscale/include/emmer/ndimage/power.py
locscale/include/emmer/ndimage/profile_tools.py
locscale/include/emmer/ndimage/simulate.py
locscale/include/emmer/pdb/__init__.py
locscale/include/emmer/pdb/common_pdb_headers.py
locscale/include/emmer/pdb/convert_pdb_to_mmcif.py
locscale/include/emmer/pdb/fitting_tools.py
locscale/include/emmer/pdb/get_associated_pdbs_for_all_emdb.py
locscale/include/emmer/pdb/get_dssp.py
locscale/include/emmer/pdb/modify_pdb.py
locscale/include/emmer/pdb/pdb_to_map.py
locscale/include/emmer/pdb/pdb_tools.py
locscale/include/emmer/pdb/pdb_utils.py
locscale/include/symmetry_emda/GenerateOperators_v9_ky4.py
locscale/include/symmetry_emda/__init__.py
locscale/include/symmetry_emda/apply_rotation_matrix.py
locscale/include/symmetry_emda/fcodes_fast.f90
