Metadata-Version: 2.1
Name: locscale
Version: 2.3.0.post1
Summary: Contrast optimization for cryo-EM maps
Home-page: https://gitlab.tudelft.nl/aj-lab/locscale
Author: Alok Bharadwaj, Arjen J. Jakobi, Reinier de Bruin
License: 3-clause BSD
Project-URL: Bug Tracker, https://gitlab.tudelft.nl/aj-lab/locscale/issues
Classifier: Development Status :: 4 - Beta
Classifier: Intended Audience :: Science/Research
Classifier: Topic :: Scientific/Engineering
Classifier: Operating System :: OS Independent
Classifier: Programming Language :: Python :: 3.7
Classifier: Programming Language :: Python :: 3.8
Classifier: License :: OSI Approved :: BSD License
Provides-Extra: mac
